double11.py
double11-1.0.0.dist-info/METADATA
double11-1.0.0.dist-info/WHEEL
double11-1.0.0.dist-info/entry_points.txt
double11-1.0.0.dist-info/top_level.txt
double11-1.0.0.dist-info/RECORD
