Metadata-Version: 2.1
Name: double11
Version: 1.0.0
Summary: double11
Home-page: https://www.pycourses.com/double12
Author: IPaisen
Author-email: admin@pycourses.com
License: MIT
Platform: UNKNOWN
Classifier: License :: OSI Approved :: MIT License
Classifier: Programming Language :: Python
Classifier: Programming Language :: Python :: 2
Classifier: Programming Language :: Python :: 3
